pushapkscript/__init__.py
pushapkscript/exceptions.py
pushapkscript/jarsigner.py
pushapkscript/manifest.py
pushapkscript/publish.py
pushapkscript/publish_config.py
pushapkscript/script.py
pushapkscript/task.py
pushapkscript/utils.py
pushapkscript/data/android-nightly.cer
pushapkscript/data/pushapk_task_schema.json
pushapkscript/test/__init__.py
pushapkscript/test/test_jarsigner.py
pushapkscript/test/test_manifest.py
pushapkscript/test/test_publish.py
pushapkscript/test/test_publish_config.py
pushapkscript/test/test_script.py
pushapkscript/test/test_task.py
pushapkscript/test/test_utils.py
pushapkscript/test/helpers/__init__.py
pushapkscript/test/helpers/mock_file.py
pushapkscript/test/helpers/task_generator.py
pushapkscript-5.0.0.dist-info/LICENSE
pushapkscript-5.0.0.dist-info/METADATA
pushapkscript-5.0.0.dist-info/WHEEL
pushapkscript-5.0.0.dist-info/entry_points.txt
pushapkscript-5.0.0.dist-info/top_level.txt
pushapkscript-5.0.0.dist-info/RECORD
