Metadata-Version: 2.1
Name: pushapkscript
Version: 5.0.0
Summary: TaskCluster Push APK Worker
Home-page: https://github.com/mozilla-releng/pushapkscript
Author: Mozilla Release Engineering
Author-email: release+python@mozilla.com
License: MPL2
Platform: UNKNOWN
Classifier: Programming Language :: Python :: 3.6
Classifier: Programming Language :: Python :: 3.7
Requires-Dist: google-api-python-client
Requires-Dist: mozapkpublisher (<5,>=4)
Requires-Dist: oauth2client
Requires-Dist: pyOpenSSL
Requires-Dist: scriptworker
